pp.py
lib/__init__.py
lib/cli.py
lib/config.py
lib/dependencies.py
lib/errors.py
lib/execution.py
lib/params.py
ppbuild-2.0.0.dist-info/licenses/LICENSE
ppbuild-2.0.0.dist-info/METADATA
ppbuild-2.0.0.dist-info/WHEEL
ppbuild-2.0.0.dist-info/entry_points.txt
ppbuild-2.0.0.dist-info/top_level.txt
ppbuild-2.0.0.dist-info/RECORD
