Metadata-Version: 2.4
Name: ppbuild
Version: 2.0.0
Summary: A declarative, language-agnostic build system and utility manager
Home-page: https://github.com/JoshCap20/pp
Author: Josh Caponigro
Project-URL: Bug Tracker, https://github.com/JoshCap20/pp/issues
Project-URL: Documentation, https://github.com/JoshCap20/pp/blob/main/TEMPLATE.md
Project-URL: Source Code, https://github.com/JoshCap20/pp
Keywords: build-system,developer-tools,automation,cli,yaml,cross-platform
Classifier: Development Status :: 4 - Beta
Classifier: Intended Audience :: Developers
Classifier: Topic :: Software Development :: Build Tools
Classifier: Topic :: System :: Systems Administration
Classifier: License :: OSI Approved :: MIT License
Classifier: Programming Language :: Python :: 3
Classifier: Programming Language :: Python :: 3.9
Classifier: Programming Language :: Python :: 3.10
Classifier: Programming Language :: Python :: 3.11
Classifier: Programming Language :: Python :: 3.12
Classifier: Programming Language :: Python :: 3.13
Classifier: Operating System :: OS Independent
Requires-Python: >=3.9
License-File: LICENSE
Requires-Dist: pyyaml>=5.1
Requires-Dist: python-dotenv>=0.19.0
Dynamic: author
Dynamic: classifier
Dynamic: description
Dynamic: description-content-type
Dynamic: home-page
Dynamic: keywords
Dynamic: license-file
Dynamic: project-url
Dynamic: requires-dist
Dynamic: requires-python
Dynamic: summary
